openspi/__init__.py
openspi/__version__.py
openspi/core.py
openspi/metadata.py
openspi/nrel.py
openspi/utils.py
openspi-0.0.5.dist-info/licenses/LICENSE.md
openspi-0.0.5.dist-info/METADATA
openspi-0.0.5.dist-info/WHEEL
openspi-0.0.5.dist-info/top_level.txt
openspi-0.0.5.dist-info/RECORD
