Metadata-Version: 2.4
Name: openspi
Version: 0.0.5
Summary: This package is designed to easily interface with the OpenSpecy package for R. Python is used for file preprocessing and post-processing, and OpenSpecy is accessed by executing R from Python.
Home-page: https://github.com/KrisHeathNREL/OpenSpecy-Python-Interface
Author: Kristopher Heath
Author-email: kheath@nrel.gov
License: MIT
Keywords: OpenSpecy,openspecy,microplastics,plastics,polymer,infrared,spectra,spectral,raman,ftir,environmental
Classifier: Programming Language :: Python :: 3
Classifier: License :: OSI Approved :: MIT License
Classifier: Operating System :: OS Independent
License-File: LICENSE.md
Requires-Dist: openpyxl>=3.1.5
Requires-Dist: pandas>=2.2.3
Requires-Dist: rpy2==3.5.16
Dynamic: author
Dynamic: classifier
Dynamic: description
Dynamic: description-content-type
Dynamic: home-page
Dynamic: license
Dynamic: license-file
Dynamic: requires-dist
Dynamic: summary
